hamsterpy/__init__.py
hamsterpy/constants.py
hamsterpy/hamsterpy.py
hamsterpy-0.0.3.dist-info/METADATA
hamsterpy-0.0.3.dist-info/WHEEL
hamsterpy-0.0.3.dist-info/top_level.txt
hamsterpy-0.0.3.dist-info/RECORD
