Metadata-Version: 2.1
Name: hamsterpy
Version: 0.0.3
Summary: HamsterPy is created for auto-farming coins in Hamster Kombat (Telegram game)
Home-page: https://github.com/KirbyRedius/HamsterPy
Author: KirbyRedius
License: UNKNOWN
Project-URL: GitHub, https://github.com/KirbyRedius/HamsterPy
Keywords: Hamster,HamsterKombat,Hamster Kombat,api.hamsterkombat.io
Platform: UNKNOWN
Classifier: Programming Language :: Python :: 3.11
Classifier: License :: OSI Approved :: MIT License
Classifier: Operating System :: OS Independent
Requires-Python: >=3.6
Requires-Dist: requests >=2.32.3
